manage.py
gencode/__init__.py
gencode/dd_models.py
gencode/ext.py
gencode/gen_code.py
gencode/swg2_class_models.py
gencode/uml_class_models.py
gencode/upgrade.py
gencode/utils.py
gencode/gencode/__init__.py
gencode/gencode/export_class2swgclass.py
gencode/gencode/gen_bo_models_code.py
gencode/gencode/gen_state_code.py
gencode/gencode/gen_swagger_code.py
gencode/gencode/gen_tests_code.py
gencode/gencode/sample/__init__.py
gencode/gencode/sample/babel.cfg
gencode/gencode/sample/config-sample.ini
gencode/gencode/sample/config.ini
gencode/gencode/sample/create_new_table_run.pys
gencode/gencode/sample/dockerignore.dock
gencode/gencode/sample/file_utils.pys
gencode/gencode/sample/gencode.xmi
gencode/gencode/sample/gitignore.git
gencode/gencode/sample/migrate_run.bat
gencode/gencode/sample/migrate_run.pys
gencode/gencode/sample/requirements.txt
gencode/gencode/sample/run.sh
gencode/gencode/sample/test__init__.pys
gencode/gencode/sample/test_run.pys
gencode/gencode/sample/utils.pys
gencode/gencode/sample/seeds/__init__.py
gencode/gencode/sample/seeds/models_rm.pys
gencode/gencode/sample/seeds/seed_dev_data.pys
gencode/gencode/sample/seeds/seed_init.pys
gencode/gencode/sample/seeds/seed_rm.pys
gencode/gencode/sample/seeds/seed_run.pys
gencode/gencode/sample/seeds/seed_utils.pys
gencode/gencode/template/Dockerfile.tmp
gencode/gencode/template/README.md
gencode/gencode/template/__init__.py
gencode/gencode/template/__init__.pys
gencode/gencode/template/config.pys
gencode/gencode/template/default.conf
gencode/gencode/template/docker-compose-dev.yaml
gencode/gencode/template/docker-compose.yaml
gencode/gencode/template/drone.tmp
gencode/gencode/template/flask_models.pys
gencode/gencode/template/flask_models_base.pys
gencode/gencode/template/gen_code_flask.yaml
gencode/gencode/template/gen_code_run.pys
gencode/gencode/template/k8s-tmp.yml
gencode/gencode/template/run.pys
gencode/gencode/template/sample.mdj
gencode/gencode/template/setup.tmp
mwgencode-1.4.4.dist-info/licenses/LICENSE.txt
mwgencode-1.4.4.dist-info/METADATA
mwgencode-1.4.4.dist-info/WHEEL
mwgencode-1.4.4.dist-info/entry_points.txt
mwgencode-1.4.4.dist-info/top_level.txt
mwgencode-1.4.4.dist-info/RECORD
