Metadata-Version: 2.4
Name: mwgencode
Version: 1.4.4
Summary: 根据starUML文档产生flask专案的代码
Home-page: https://bitbucket.org/maxwin-inc/gencode/src/
Author: cxhjet
Author-email: cxhjet@qq.com
Classifier: Intended Audience :: Developers
Classifier: License :: OSI Approved :: BSD License
Classifier: Operating System :: OS Independent
Classifier: Programming Language :: Python :: 3.5
Classifier: Programming Language :: Python :: 3.6
Classifier: Programming Language :: Python :: 3.7
Classifier: Programming Language :: Python :: 3.8
Classifier: Programming Language :: Python :: 3.9
Classifier: Programming Language :: Python :: 3.10
Classifier: Programming Language :: Python :: 3.11
License-File: LICENSE.txt
Requires-Dist: mwutils>=0.1.41
Requires-Dist: mwauth>=0.4.49
Requires-Dist: mwsdk>=0.3.2
Requires-Dist: mwpermission>=0.1.26
Requires-Dist: mw-aiohttp-session>=0.1.13
Requires-Dist: mw-aiohttp-babel>=0.1.7
Requires-Dist: mw-aiohttp-security>=0.1.13
Requires-Dist: SQLAlchemy>=1.4.31
Requires-Dist: pyJWT
Requires-Dist: python-consul
Requires-Dist: flask_migrate
Requires-Dist: flask-babel
Requires-Dist: Flask-Cors
Requires-Dist: Flask-Redis
Requires-Dist: Flask-SQLAlchemy>=2.5.1
Requires-Dist: geojson
Requires-Dist: redis>=4.0.2
Requires-Dist: connexion[swagger-ui]>=2.11.1
Requires-Dist: Flask>=2.0.2
Requires-Dist: Werkzeug>=0.15.5
Requires-Dist: yarl>=1.4.2
Requires-Dist: xlrd
Requires-Dist: xlsxwriter
Requires-Dist: aioredis
Requires-Dist: aiohttp_swagger
Dynamic: author
Dynamic: author-email
Dynamic: classifier
Dynamic: description
Dynamic: home-page
Dynamic: license-file
Dynamic: requires-dist
Dynamic: summary
